MANIFEST.in
setup.py
docs/HISTORY.txt
src/menhir/__init__.py
src/menhir.contenttype.image.egg-info/PKG-INFO
src/menhir.contenttype.image.egg-info/SOURCES.txt
src/menhir.contenttype.image.egg-info/dependency_links.txt
src/menhir.contenttype.image.egg-info/entry_points.txt
src/menhir.contenttype.image.egg-info/namespace_packages.txt
src/menhir.contenttype.image.egg-info/not-zip-safe
src/menhir.contenttype.image.egg-info/requires.txt
src/menhir.contenttype.image.egg-info/top_level.txt
src/menhir/contenttype/__init__.py
src/menhir/contenttype/image/README.txt
src/menhir/contenttype/image/__init__.py
src/menhir/contenttype/image/configure.zcml
src/menhir/contenttype/image/ftesting.zcml
src/menhir/contenttype/image/image.png
src/menhir/contenttype/image/image.py
src/menhir/contenttype/image/library.py
src/menhir/contenttype/image/tests.py
src/menhir/contenttype/image/views.py
src/menhir/contenttype/image/resources/popup.js
src/menhir/contenttype/image/views_templates/imageview.pt