Metadata-Version: 1.0
Name: menhir.contenttype.image
Version: 0.3
Summary: Dolmen content-type extension : image
Home-page: http://tracker.trollfot.org/
Author: Souheil Chelfouh
Author-email: souheil@chelfouh.com
License: GPL
Download-URL: http://pypi.python.org/pypi/menhir.contenttype.image
Keywords: Grok Zope3 CMS Dolmen
Platform: Any
Classifier: Development Status :: 4 - Beta
Classifier: Environment :: Web Environment
Classifier: Framework :: Zope3
Classifier: Intended Audience :: Other Audience
Classifier: License :: OSI Approved :: GNU General Public License (GPL)
Classifier: Operating System :: OS Independent
Classifier: Programming Language :: Python
